Metadata-Version: 2.1
Name: PyOneLiner
Version: 0.0.1
Summary: This package implement a code OneLiner for python (write a script and get it in oneline).
Home-page: https://github.com/mauricelambert/PyOneLiner
Author: Maurice Lambert
Author-email: mauricelambert434@gmail.com
License: UNKNOWN
Platform: UNKNOWN
Classifier: Programming Language :: Python
Classifier: Development Status :: 5 - Production/Stable
Classifier: Environment :: Console
Classifier: Natural Language :: English
Classifier: Operating System :: OS Independent
Classifier: Programming Language :: Python :: 3.8
Requires-Python: >=3.6
